brasil.gov.barra-3.0.11-nspkg.pth
brasil/gov/barra/__init__.py
brasil/gov/barra/config.py
brasil/gov/barra/configure.zcml
brasil/gov/barra/interfaces.py
brasil/gov/barra/profiles.zcml
brasil/gov/barra/setuphandlers.py
brasil/gov/barra/testing.py
brasil/gov/barra/browser/__init__.py
brasil/gov/barra/browser/barra.py
brasil/gov/barra/browser/configure.zcml
brasil/gov/barra/browser/helper.py
brasil/gov/barra/browser/templates/barra.pt
brasil/gov/barra/browser/templates/barra_js.pt
brasil/gov/barra/controlpanel/__init__.py
brasil/gov/barra/controlpanel/barra.py
brasil/gov/barra/controlpanel/configure.zcml
brasil/gov/barra/locales/brasil.gov.barra-manual.pot
brasil/gov/barra/locales/brasil.gov.barra.pot
brasil/gov/barra/locales/manual.pot
brasil/gov/barra/locales/plone.pot
brasil/gov/barra/locales/pt_BR/LC_MESSAGES/brasil.gov.barra.po
brasil/gov/barra/locales/pt_BR/LC_MESSAGES/plone.po
brasil/gov/barra/profiles/default/browserlayer.xml
brasil/gov/barra/profiles/default/controlpanel.xml
brasil/gov/barra/profiles/default/metadata.xml
brasil/gov/barra/profiles/default/propertiestool.xml
brasil/gov/barra/profiles/default/viewlets.xml
brasil/gov/barra/profiles/uninstall/browserlayer.xml
brasil/gov/barra/profiles/uninstall/controlpanel.xml
brasil/gov/barra/static/barra.js
brasil/gov/barra/static/ico-brasil.png
brasil/gov/barra/tests/__init__.py
brasil/gov/barra/tests/barra.txt
brasil/gov/barra/tests/painel.txt
brasil/gov/barra/tests/test_controlpanel.py
brasil/gov/barra/tests/test_functional.py
brasil/gov/barra/tests/test_helper.py
brasil/gov/barra/tests/test_setup.py
brasil/gov/barra/tests/test_upgrades.py
brasil/gov/barra/upgrades/__init__.py
brasil/gov/barra/upgrades/configure.zcml
brasil/gov/barra/upgrades/v2000/__init__.py
brasil/gov/barra/upgrades/v2000/configure.zcml
brasil.gov.barra-3.0.11.dist-info/DESCRIPTION.rst
brasil.gov.barra-3.0.11.dist-info/METADATA
brasil.gov.barra-3.0.11.dist-info/RECORD
brasil.gov.barra-3.0.11.dist-info/WHEEL
brasil.gov.barra-3.0.11.dist-info/entry_points.txt
brasil.gov.barra-3.0.11.dist-info/metadata.json
brasil.gov.barra-3.0.11.dist-info/namespace_packages.txt
brasil.gov.barra-3.0.11.dist-info/top_level.txt
