Metadata-Version: 2.0
Name: brasil.gov.barra
Version: 3.0.11
Summary: .gov.br: Barra de Identidade 
Home-page: https://github.com/plonegovbr/brasil.gov.barra
Author: PloneGov.Br
Author-email: gov@plone.org.br
License: UNKNOWN
Keywords: brasil.gov.br barra plone plonegovbr temas
Platform: UNKNOWN
Classifier: Development Status :: 4 - Beta
Classifier: Environment :: Web Environment
Classifier: Framework :: Plone
Classifier: Framework :: Plone :: 4.3
Classifier: Intended Audience :: Developers
Classifier: License :: OSI Approved :: GNU General Public License v2 (GPLv2)
Classifier: Operating System :: OS Independent
Classifier: Programming Language :: Python :: 2.7
Classifier: Programming Language :: Python
Classifier: Topic :: Internet :: WWW/HTTP
Classifier: Topic :: Internet :: WWW/HTTP :: Dynamic Content
Classifier: Topic :: Software Development :: Libraries :: Python Modules
Provides-Extra: develop
Provides-Extra: test
Requires-Dist: Products.CMFPlone (>=4.3)
Requires-Dist: plone.api
Requires-Dist: setuptools
Provides-Extra: develop
Requires-Dist: Sphinx; extra == 'develop'
Requires-Dist: manuel; extra == 'develop'
Requires-Dist: pep8; extra == 'develop'
Requires-Dist: setuptools-flakes; extra == 'develop'
Provides-Extra: test
Requires-Dist: interlude; extra == 'test'
Requires-Dist: plone.app.testing; extra == 'test'
Requires-Dist: requests; extra == 'test'
